thea/__init__.py
thea/__main__.py
thea/base_itemstore.py
thea/cli.py
thea/comm_handlers/__init__.py
thea/comm_handlers/mosquitto_broker.py
thea/comm_handlers/mqtt.py
thea/comm_handlers/mqtt_constants.py
thea/comm_handlers/mqtt_new_config.py
thea/communicator_types.py
thea/communicators.py
thea/dev_mqtt_entrypoint.py
thea/env_thing_linker.py
thea/environment/__init__.py
thea/environment/default.py
thea/environment/defenitions.py
thea/environment/environment.py
thea/environment/updaters/__init__.py
thea/environment/updaters/astronomical.py
thea/environment/updaters/date_time.py
thea/environment/updaters/human_readable.py
thea/environment/updaters/irradiance.py
thea/environment/updaters/season.py
thea/environment/updaters/stacked_linear_model.py
thea/environment/updaters/workday.py
thea/exceptions.py
thea/functional_endpoints.py
thea/logging.ini
thea/logging_setup.py
thea/mqtt_hardware_module.py
thea/mqtt_hardware_types.py
thea/mqtt_send_command.py
thea/pretty_printing.py
thea/thea_world.py
thea/thing_types.py
thea/thing_updaters/__init__.py
thea/thing_updaters/percentage_switcher.py
thea/things.py
thea-0.0.1.dist-info/entry_points.txt
thea-0.0.1.dist-info/LICENSE.md
thea-0.0.1.dist-info/WHEEL
thea-0.0.1.dist-info/METADATA
thea-0.0.1.dist-info/RECORD
